openlayer_guardrails/__init__.py
openlayer_guardrails/pii.py
openlayer_guardrails-0.1.0.dist-info/METADATA
openlayer_guardrails-0.1.0.dist-info/WHEEL
openlayer_guardrails-0.1.0.dist-info/RECORD
