Metadata-Version: 2.4
Name: openlayer-guardrails
Version: 0.1.0
Summary: Guardrails that can be used to check inputs and outputs of functions and works well with Openlayer tracing.
Requires-Python: >=3.10
Requires-Dist: openlayer>=0.2.0a89
Provides-Extra: pii
Requires-Dist: presidio-analyzer>=2.2.0; extra == 'pii'
Requires-Dist: presidio-anonymizer>=2.2.0; extra == 'pii'
